download_openaq.py
download_openaq-0.0.6.dist-info/DESCRIPTION.rst
download_openaq-0.0.6.dist-info/METADATA
download_openaq-0.0.6.dist-info/RECORD
download_openaq-0.0.6.dist-info/WHEEL
download_openaq-0.0.6.dist-info/metadata.json
download_openaq-0.0.6.dist-info/top_level.txt
