Metadata-Version: 2.0
Name: download-openaq
Version: 0.0.6
Summary: Downloads OpenAQ CSV data from S3
Home-page: UNKNOWN
Author: Development Seed
Author-email: aimee@developmentseed.org,rosariosicuranza@gmail.com
License: MIT
Platform: UNKNOWN
Requires-Dist: boto3
Requires-Dist: pandas
